design/verilog/SFU/sfu.v
module sfu #( 
    parameter bw = 4,
    parameter psum_bw = 16,
    parameter col = 8,
    parameter row = 8
    ) (
    input clk,
    input reset,
    input acc_i, // 0 -> O.S 1 -> W.S
    input [col*psum_bw-1:0] psum_in,
    output [col*psum_bw-1:0] psum_out
    );

    reg acc_q;
    //reg valid_q;
    reg acc_out_q;

    reg [col*psum_bw-1:0] psum_q;

    wire [col*psum_bw-1:0] temp_psum_w;
    wire [col*psum_bw-1:0] temp_relu_psum_w;
    wire [col*psum_bw-1:0] temp_relu_only_psum_w;
    

    genvar k;
    generate
        for (k=0;k<=col-1;k=k+1) begin : sfp_out_assign
        
            // ReLU
            assign temp_relu_psum_w[((k+1)*psum_bw)-1:k*psum_bw] = psum_q[((k+1)*psum_bw)-1] ? 0 : psum_q[((k+1)*psum_bw)-1:k*psum_bw];         
            assign temp_relu_only_psum_w[((k+1)*psum_bw)-1:k*psum_bw] =  psum_in[((k+1)*psum_bw)-1] ? 0 : psum_in[((k+1)*psum_bw)-1:k*psum_bw];
            
            assign psum_out[(k+1)*psum_bw-1:k*psum_bw] = acc_out_q ? temp_relu_psum_w[((k+1)*psum_bw)-1:k*psum_bw] : temp_relu_only_psum_w[((k+1)*psum_bw)-1:k*psum_bw];
        end
    endgenerate
    

    integer j;
    always @(posedge clk, posedge reset) begin
        if(reset) begin
            acc_q <= 0;
            psum_q <= 0;
            acc_out_q <= 0;
        end
        else begin
            acc_q <= acc_i;
            if(~acc_q && acc_i) begin
                psum_q <= psum_in; 
                acc_out_q <= 1'b0;
            end
            else if(acc_q && acc_i) begin
                // Accumulate
                psum_q <= psum_q + psum_in; 
                acc_out_q <= 1'b0;
            end
            else if(acc_q && ~acc_i) begin
                acc_out_q <= 1'b1;
            end
            else if(~acc_q) begin
                acc_out_q <= 1'b0;
            end 
        end
    end

endmodule

verification/sfu/sfu_tb.v
module sfu_tb;

parameter bw = 4;
parameter col = 8;
parameter row = 8;
parameter psum_bw = 16;

reg clk = 0;
reg reset = 1;  
reg  [psum_bw*col-1:0] psum;
reg  [psum_bw*col-1:0] psum_in;
reg acc;
reg acc_i;
wire [psum_bw*col-1:0] sfu_out;
integer psum_file, acc_file;
integer psum_result, acc_result;

sfu #(
    .bw     (bw),
    .col    (col),
    .row    (row),
    .psum_bw(psum_bw)
) sfu_inst (
    .clk        (clk),
    .reset      (reset),
    .acc_i      (acc_i),
    .psum_in    (psum_in),
    .psum_out   (sfu_out)
);

always #5 clk = ~clk;

initial begin
    $dumpfile("sfu_tb.vcd");
    $dumpvars(0,sfu_tb);

    clk = 1;
    psum_in = {psum_bw*col{1'b0}};
    acc_i = 0;
    #20
    reset = 1'b0;


    psum_file = $fopen("psum.txt", "r");
    if (psum_file == 0) begin
        $display("Error opening psum.txt");
        $finish;
    end

    acc_file = $fopen("acc.txt", "r");
    if (acc_file == 0) begin
        $display("Error opening acc.txt");
        $finish;
    end

    while (!$feof(psum_file) && !$feof(acc_file)) begin
            // Read the next value from each file
            psum_result = $fscanf(psum_file, "%h,", psum); 
            acc_result = $fscanf(acc_file, "%b,", acc);

            if (psum_result == 1 && acc_result == 1) begin
                psum_in = psum;  // Apply the stimulus to stim_in1
                acc_i = acc;  // Apply the stimulus to stim_in2
                #10;  // Wait for 10 time units
            end
        end
    $fclose(psum_file);
    $fclose(acc_file);
    #20
    $finish;
end

endmodule

verification/sfu/sfu_tb.vcd
$date
	Sun Dec 01 14:14:13 2024
$end
$version
	Icarus Verilog
$end
$timescale
	1s
$end
$scope module sfu_tb $end
$var wire 128 ! sfu_out [127:0] $end
$var parameter 32 " bw $end
$var parameter 32 # col $end
$var parameter 32 $ psum_bw $end
$var parameter 32 % row $end
$var reg 1 & acc $end
$var reg 1 ' acc_i $end
$var reg 1 ( clk $end
$var reg 128 ) psum [127:0] $end
$var reg 128 * psum_in [127:0] $end
$var reg 1 + reset $end
$var integer 32 , acc_file [31:0] $end
$var integer 32 - acc_result [31:0] $end
$var integer 32 . psum_file [31:0] $end
$var integer 32 / psum_result [31:0] $end
$scope module sfu_inst $end
$var wire 1 ' acc_i $end
$var wire 1 ( clk $end
$var wire 128 0 psum_in [127:0] $end
$var wire 1 + reset $end
$var wire 128 1 temp_relu_psum_w [127:0] $end
$var wire 128 2 temp_relu_only_psum_w [127:0] $end
$var wire 128 3 psum_out [127:0] $end
$var parameter 32 4 bw $end
$var parameter 32 5 col $end
$var parameter 32 6 psum_bw $end
$var parameter 32 7 row $end
$var reg 1 8 acc_out_q $end
$var reg 1 9 acc_q $end
$var reg 128 : psum_q [127:0] $end
$scope begin sfp_out_assign[0] $end
$var parameter 2 ; k $end
$upscope $end
$scope begin sfp_out_assign[1] $end
$var parameter 2 < k $end
$upscope $end
$scope begin sfp_out_assign[2] $end
$var parameter 3 = k $end
$upscope $end
$scope begin sfp_out_assign[3] $end
$var parameter 3 > k $end
$upscope $end
$scope begin sfp_out_assign[4] $end
$var parameter 4 ? k $end
$upscope $end
$scope begin sfp_out_assign[5] $end
$var parameter 4 @ k $end
$upscope $end
$scope begin sfp_out_assign[6] $end
$var parameter 4 A k $end
$upscope $end
$scope begin sfp_out_assign[7] $end
$var parameter 4 B k $end
$upscope $end
$upscope $end
$upscope $end
$enddefinitions $end
$comment Show the parameter values. $end
$dumpall
b111 B
b110 A
b101 @
b100 ?
b11 >
b10 =
b1 <
b0 ;
b1000 7
b10000 6
b1000 5
b100 4
b1000 %
b10000 $
b1000 #
b100 "
$end
#0
$dumpvars
b0 :
09
08
b0 3
b0 2
b0 1
b0 0
bx /
bx .
bx -
bx ,
1+
b0 *
bx )
1(
0'
x&
b0 !
$end
#5
0(
#10
1(
#15
0(
#20
1(
b1 -
0&
b1 /
b0 )
b10000000000000000000000000000100 ,
b10000000000000000000000000000011 .
0+
#25
0(
#30
b10000000000000001000000000000000100000000000000010000000000000001000000000000000100000000000000010000000000000001 1
b10000000000000001000000000000000100000000000000010000000000000001000000000000000100000000000000010000000000000001 :
19
b10000000000000001000000000000000100000000000000010000000000000001000000000000000100000000000000010000000000000001 !
b10000000000000001000000000000000100000000000000010000000000000001000000000000000100000000000000010000000000000001 3
b10000000000000001000000000000000100000000000000010000000000000001000000000000000100000000000000010000000000000001 2
1(
1'
b10000000000000001000000000000000100000000000000010000000000000001000000000000000100000000000000010000000000000001 *
b10000000000000001000000000000000100000000000000010000000000000001000000000000000100000000000000010000000000000001 0
1&
b10000000000000001000000000000000100000000000000010000000000000001000000000000000100000000000000010000000000000001 )
#35
0(
#40
b10000000000000000000000000000000100000000000000000000000000000001000000000000000000000000000000000010 1
b11111111111110100000000000010000111111111001001000000000000100001111111110010010000000000001000011111111100100100000000000000010 :
b1111000000000000000000000000000011110000000000000000000000000000111100000000000000000000000000000001 !
b1111000000000000000000000000000011110000000000000000000000000000111100000000000000000000000000000001 3
b1111000000000000000000000000000011110000000000000000000000000000111100000000000000000000000000000001 2
1(
b11111111111110010000000000001111111111111001000100000000000011111111111110010001000000000000111111111111100100010000000000000001 *
b11111111111110010000000000001111111111111001000100000000000011111111111110010001000000000000111111111111100100010000000000000001 0
b11111111111110010000000000001111111111111001000100000000000011111111111110010001000000000000111111111111100100010000000000000001 )
#45
0(
#50
b10101000000000000000000000000000101010000000000000000000000000001010100000000000000000000000000000111 1
b11111111111111110000000000010101111111111001011100000000000101011111111110010111000000000001010111111111100101110000000000000111 :
b1010000000000000101000000000000010100000000000001010000000000000101000000000000010100000000000001010000000000000101 !
b1010000000000000101000000000000010100000000000001010000000000000101000000000000010100000000000001010000000000000101 3
b1010000000000000101000000000000010100000000000001010000000000000101000000000000010100000000000001010000000000000101 2
1(
b1010000000000000101000000000000010100000000000001010000000000000101000000000000010100000000000001010000000000000101 *
b1010000000000000101000000000000010100000000000001010000000000000101000000000000010100000000000001010000000000000101 0
b1010000000000000101000000000000010100000000000001010000000000000101000000000000010100000000000001010000000000000101 )
#55
0(
#60
b100000000000011000000000000000000000000000000110000000000000000000000000000001100000000000000000000000000000001010 1
b100000000000011000111111111001101000000000000110001111111110011010000000000001100011111111100110100000000000001010 :
b110000000000000011000000000000001100000000000000110000000000000011000000000000001100000000000000110000000000000011 !
b110000000000000011000000000000001100000000000000110000000000000011000000000000001100000000000000110000000000000011 3
b110000000000000011000000000000001100000000000000110000000000000011000000000000001100000000000000110000000000000011 2
1(
b110000000000000011000000000000001100000000000000110000000000000011000000000000001100000000000000110000000000000011 *
b110000000000000011000000000000001100000000000000110000000000000011000000000000001100000000000000110000000000000011 0
b110000000000000011000000000000001100000000000000110000000000000011000000000000001100000000000000110000000000000011 )
#65
0(
#70
b1110000000000011101000000000000000000000000000111010000000000000000000000000001110100000000000000000000000000001111 1
b1110000000000011101111111111001111100000000000111011111111110011111000000000001110111111111100111110000000000001111 :
b1010000000000000101000000000000010100000000000001010000000000000101000000000000010100000000000001010000000000000101 !
b1010000000000000101000000000000010100000000000001010000000000000101000000000000010100000000000001010000000000000101 3
b1010000000000000101000000000000010100000000000001010000000000000101000000000000010100000000000001010000000000000101 2
1(
b1010000000000000101000000000000010100000000000001010000000000000101000000000000010100000000000001010000000000000101 *
b1010000000000000101000000000000010100000000000001010000000000000101000000000000010100000000000001010000000000000101 0
b1010000000000000101000000000000010100000000000001010000000000000101000000000000010100000000000001010000000000000101 )
#75
0(
#80
b11000000000000100010000000000000000000000000001000100000000000000000000000000010001000000000000000000000000000010100 1
b11000000000000100010111111111010010000000000001000101111111110100100000000000010001011111111101001000000000000010100 :
1(
#85
0(
#90
b1100000000000011100000000000000000000000000000111000000000000000000000000000001110000000000000000000000000000001101 1
b1100000000000011100111111111001111000000000000111001111111110011110000000000001110011111111100111100000000000001101 :
b0 !
b0 3
b0 2
1(
b11111111111110011111111111111001111111111111100111111111111110011111111111111001111111111111100111111111111110011111111111111001 *
b11111111111110011111111111111001111111111111100111111111111110011111111111111001111111111111100111111111111110011111111111111001 0
b11111111111110011111111111111001111111111111100111111111111110011111111111111001111111111111100111111111111110011111111111111001 )
#95
0(
#100
b11000000000000100010000000000000000000000000001000100000000000000000000000000010001000000000000000000000000000010011 1
b11000000000000100010111111111010010000000000001000101111111110100100000000000010001011111111101001000000000000010011 :
b1100000000000000110000000000000011000000000000001100000000000000110000000000000011000000000000001100000000000000110 !
b1100000000000000110000000000000011000000000000001100000000000000110000000000000011000000000000001100000000000000110 3
b1100000000000000110000000000000011000000000000001100000000000000110000000000000011000000000000001100000000000000110 2
1(
b1100000000000000110000000000000011000000000000001100000000000000110000000000000011000000000000001100000000000000110 *
b1100000000000000110000000000000011000000000000001100000000000000110000000000000011000000000000001100000000000000110 0
b1100000000000000110000000000000011000000000000001100000000000000110000000000000011000000000000001100000000000000110 )
#105
0(
#110
18
09
b11000000000000100010000000000000000000000000001000100000000000000000000000000010001000000000000000000000000000010011 !
b11000000000000100010000000000000000000000000001000100000000000000000000000000010001000000000000000000000000000010011 3
b0 2
1(
0'
b0 *
b0 0
0&
b0 )
#115
0(
#120
b0 !
b0 3
08
1(
#125
0(
#130
1(
b11111111111110011111111111111001111111111111100111111111111110011111111111111001111111111111100111111111111110011111111111111001 *
b11111111111110011111111111111001111111111111100111111111111110011111111111111001111111111111100111111111111110011111111111111001 0
b11111111111110011111111111111001111111111111100111111111111110011111111111111001111111111111100111111111111110011111111111111001 )
#135
0(
#140
b1010000000000000101000000000000010100000000000001010000000000000101000000000000010100000000000001010000000000000101 !
b1010000000000000101000000000000010100000000000001010000000000000101000000000000010100000000000001010000000000000101 3
b1010000000000000101000000000000010100000000000001010000000000000101000000000000010100000000000001010000000000000101 2
1(
b1010000000000000101000000000000010100000000000001010000000000000101000000000000010100000000000001010000000000000101 *
b1010000000000000101000000000000010100000000000001010000000000000101000000000000010100000000000001010000000000000101 0
b1010000000000000101000000000000010100000000000001010000000000000101000000000000010100000000000001010000000000000101 )
#145
0(
#150
b0 !
b0 3
b0 2
1(
b11111111111110011111111111111001111111111111100111111111111110011111111111111001111111111111100111111111111110011111111111111001 *
b11111111111110011111111111111001111111111111100111111111111110011111111111111001111111111111100111111111111110011111111111111001 0
b11111111111110011111111111111001111111111111100111111111111110011111111111111001111111111111100111111111111110011111111111111001 )
#155
0(
#160
1(
b0 *
b0 0
b0 )
#165
0(
#170
1(
b11111111111110011111111111111001111111111111100111111111111110011111111111111001111111111111100111111111111110011111111111111001 *
b11111111111110011111111111111001111111111111100111111111111110011111111111111001111111111111100111111111111110011111111111111001 0
b11111111111110011111111111111001111111111111100111111111111110011111111111111001111111111111100111111111111110011111111111111001 )
